lined/__init__.py
lined/base.py
lined/recipes.py
lined/simple.py
lined/tools.py
lined/util.py
lined/examples/__init__.py
lined/scrap/__init__.py
lined/scrap/w_streamz.py
lined-0.0.32.dist-info/LICENSE
lined-0.0.32.dist-info/METADATA
lined-0.0.32.dist-info/WHEEL
lined-0.0.32.dist-info/top_level.txt
lined-0.0.32.dist-info/RECORD
