Metadata-Version: 2.1
Name: lined
Version: 0.0.32
Summary: Building simple pipelines simply.
Home-page: https://github.com/otosense/lined
Author: OtoSense
License: apache-2.0
Keywords: streams,pipelines
Platform: any
Requires-Dist: i2
